{
  "version": "0x303 (TLS 1.2)",
  "ciphers": [
    "{0x6A, 0x6A} GREASE",
    "{0x13, 0x01} TLS_AES_128_GCM_SHA256",
    "{0x13, 0x02} TLS_AES_256_GCM_SHA384",
    "{0x13, 0x03} TLS_CHACHA20_POLY1305_SHA256",
    "{0xC0, 0x2B} TLS_ECDHE_ECDSA_WITH_AES_128_GCM_SHA256",
    "{0xC0, 0x2F} TLS_ECDHE_RSA_WITH_AES_128_GCM_SHA256",
    "{0xC0, 0x2C} TLS_ECDHE_ECDSA_WITH_AES_256_GCM_SHA384",
    "{0xC0, 0x30} TLS_ECDHE_RSA_WITH_AES_256_GCM_SHA384",
    "{0xCC, 0xA9} TLS_ECDHE_ECDSA_WITH_CHACHA20_POLY1305_SHA256",
    "{0xCC, 0xA8} TLS_ECDHE_RSA_WITH_CHACHA20_POLY1305_SHA256",
    "{0xC0, 0x13} TLS_ECDHE_RSA_WITH_AES_128_CBC_SHA",
    "{0xC0, 0x14} TLS_ECDHE_RSA_WITH_AES_256_CBC_SHA",
    "{0x00, 0x9C} TLS_RSA_WITH_AES_128_GCM_SHA256",
    "{0x00, 0x9D} TLS_RSA_WITH_AES_256_GCM_SHA384",
    "{0x00, 0x2F} TLS_RSA_WITH_AES_128_CBC_SHA",
    "{0x00, 0x35} TLS_RSA_WITH_AES_256_CBC_SHA"
  ],
  "compressionMethods": [
    "No Compression (0x00)"
  ],
  "extensions": [
    {
      "type": "GREASE",
      "decimal": 27242,
      "values": []
    },
    {
      "type": "UNKNOWN",
      "decimal": 17513,
      "values": [
        "0000 - 00 03 02 68 32                                 ...h2"
      ]
    },
    {
      "type": "ec_point_formats",
      "decimal": 11,
      "values": [
        "uncompressed (0)"
      ]
    },
    {
      "type": "compress_certificate",
      "decimal": 27,
      "values": [
        "0000 - 02 00 02                                       ..."
      ]
    },
    {
      "type": "signed_certificate_timestamps",
      "decimal": 18,
      "values": []
    },
    {
      "type": "UNKNOWN",
      "decimal": 65037,
      "values": [
        "0000 - 00 00 01 00 01 9f 00 20-8e 6b 56 a8 a9 82 fd   ....... .kV....",
        "000f - ef b6 7c 03 2f 8e c3 d5-b8 04 be 26 ae 1d 38   ..|./......&..8",
        "001e - 5c 7b 0f 49 fb d2 3c 13-6d 2c 00 90 ac 40 a3   \\{.I..<.m,...@.",
        "002d - 95 7f bf 4b 9b 68 78 6d-ae 5f 06 df e5 d7 0d   ...K.hxm._.....",
        "003c - a0 6d 6f d6 2e ed 26 6d-36 fd d2 17 ef d5 ca   .mo...&m6......",
        "004b - 1a 42 98 e7 31 af 7d f6-69 92 b1 eb 17 b1 60   .B..1.}.i.....`",
        "005a - 72 18 85 e6 84 c1 25 aa-8d 1e f4 5c 30 a7 e8   r.....%....\\0..",
        "0069 - 63 73 18 9c 60 a7 e6 d6-b2 8b 33 3b 7a 79 b5   cs..`.....3;zy.",
        "0078 - 30 eb 7c f7 15 e4 93 c0-4a a1 34 a7 fe dd 26   0.|.....J.4...&",
        "0087 - 1c 5a a2 23 cf bf 14 a5-32 27 9a c5 da 62 27   .Z.#....2'...b'",
        "0096 - 3d 9a b1 c7 8d fe 0e 77-46 bc 6e 9c 30 7e 67   =......wF.n.0~g",
        "00a5 - a7 26 a4 f1 0e c3 95 28-f4 41 4c cc f2 24 52   .&.....(.AL..$R",
        "00b4 - f4 a0 c5 9e f3 80                              ......"
      ]
    },
    {
      "type": "psk_key_exchange_modes",
      "decimal": 45,
      "values": [
        "psk_dhe_ke (1)"
      ]
    },
    {
      "type": "signature_algorithms",
      "decimal": 13,
      "values": [
        "ecdsa_secp256r1_sha256 (0x0403)",
        "rsa_pss_rsae_sha256 (0x0804)",
        "rsa_pkcs1_sha256 (0x0401)",
        "ecdsa_secp384r1_sha384 (0x0503)",
        "rsa_pss_rsae_sha384 (0x0805)",
        "rsa_pkcs1_sha384 (0x0501)",
        "rsa_pss_rsae_sha512 (0x0806)",
        "rsa_pkcs1_sha512 (0x0601)"
      ]
    },
    {
      "type": "key_share",
      "decimal": 51,
      "values": [
        "NamedGroup: GREASE (23130)",
        "key_exchange:  (len=1): 00",
        "NamedGroup: ecdh_x25519 (29)",
        "key_exchange:  (len=32): 9BFE3198C3402328A4DE416CD65F6CB6E06DCBC38B82BE7928D7D535EE884479"
      ]
    },
    {
      "type": "extended_master_secret",
      "decimal": 23,
      "values": []
    },
    {
      "type": "server_name",
      "decimal": 0,
      "values": [
        "0000 - 00 1c 00 00 19 74 6c 73-2e 64 61 2d 63 6f 6c   .....tls.da-col",
        "000f - 6c 65 63 74 2e 75 6c 69-78 65 65 2e 6f 72 67   lect.ulixee.org"
      ]
    },
    {
      "type": "application_layer_protocol_negotiation",
      "decimal": 16,
      "values": [
        "h2",
        "http/1.1"
      ]
    },
    {
      "type": "status_request",
      "decimal": 5,
      "values": [
        "0000 - 01 00 00 00 00                                 ....."
      ]
    },
    {
      "type": "session_ticket",
      "decimal": 35,
      "values": []
    },
    {
      "type": "supported_groups",
      "decimal": 10,
      "values": [
        "GREASE (23130)",
        "ecdh_x25519 (29)",
        "secp256r1 (P-256) (23)",
        "secp384r1 (P-384) (24)"
      ]
    },
    {
      "type": "supported_versions",
      "decimal": 43,
      "values": [
        "GREASE (47802)",
        "TLS 1.3 (772)",
        "TLS 1.2 (771)"
      ]
    },
    {
      "type": "renegotiate",
      "decimal": 65281,
      "values": [
        "<EMPTY>"
      ]
    },
    {
      "type": "GREASE",
      "decimal": 31354,
      "values": [
        "0000 - 00                                             ."
      ]
    },
    {
      "type": "padding",
      "decimal": 21,
      "values": [
        "0000 - 00                                             ."
      ]
    }
  ]
}
