{
  "version": "0x303 (TLS 1.2)",
  "ciphers": [
    "{0x2A, 0x2A} GREASE",
    "{0x13, 0x01} TLS_AES_128_GCM_SHA256",
    "{0x13, 0x02} TLS_AES_256_GCM_SHA384",
    "{0x13, 0x03} TLS_CHACHA20_POLY1305_SHA256",
    "{0xC0, 0x2B} TLS_ECDHE_ECDSA_WITH_AES_128_GCM_SHA256",
    "{0xC0, 0x2F} TLS_ECDHE_RSA_WITH_AES_128_GCM_SHA256",
    "{0xC0, 0x2C} TLS_ECDHE_ECDSA_WITH_AES_256_GCM_SHA384",
    "{0xC0, 0x30} TLS_ECDHE_RSA_WITH_AES_256_GCM_SHA384",
    "{0xCC, 0xA9} TLS_ECDHE_ECDSA_WITH_CHACHA20_POLY1305_SHA256",
    "{0xCC, 0xA8} TLS_ECDHE_RSA_WITH_CHACHA20_POLY1305_SHA256",
    "{0xC0, 0x13} TLS_ECDHE_RSA_WITH_AES_128_CBC_SHA",
    "{0xC0, 0x14} TLS_ECDHE_RSA_WITH_AES_256_CBC_SHA",
    "{0x00, 0x9C} TLS_RSA_WITH_AES_128_GCM_SHA256",
    "{0x00, 0x9D} TLS_RSA_WITH_AES_256_GCM_SHA384",
    "{0x00, 0x2F} TLS_RSA_WITH_AES_128_CBC_SHA",
    "{0x00, 0x35} TLS_RSA_WITH_AES_256_CBC_SHA"
  ],
  "compressionMethods": [
    "No Compression (0x00)"
  ],
  "extensions": [
    {
      "type": "GREASE",
      "decimal": 64250,
      "values": []
    },
    {
      "type": "supported_groups",
      "decimal": 10,
      "values": [
        "GREASE (64250)",
        "ecdh_x25519 (29)",
        "secp256r1 (P-256) (23)",
        "secp384r1 (P-384) (24)"
      ]
    },
    {
      "type": "psk_key_exchange_modes",
      "decimal": 45,
      "values": [
        "psk_dhe_ke (1)"
      ]
    },
    {
      "type": "status_request",
      "decimal": 5,
      "values": [
        "0000 - 01 00 00 00 00                                 ....."
      ]
    },
    {
      "type": "session_ticket",
      "decimal": 35,
      "values": []
    },
    {
      "type": "renegotiate",
      "decimal": 65281,
      "values": [
        "<EMPTY>"
      ]
    },
    {
      "type": "supported_versions",
      "decimal": 43,
      "values": [
        "GREASE (31354)",
        "TLS 1.3 (772)",
        "TLS 1.2 (771)"
      ]
    },
    {
      "type": "signed_certificate_timestamps",
      "decimal": 18,
      "values": []
    },
    {
      "type": "signature_algorithms",
      "decimal": 13,
      "values": [
        "ecdsa_secp256r1_sha256 (0x0403)",
        "rsa_pss_rsae_sha256 (0x0804)",
        "rsa_pkcs1_sha256 (0x0401)",
        "ecdsa_secp384r1_sha384 (0x0503)",
        "rsa_pss_rsae_sha384 (0x0805)",
        "rsa_pkcs1_sha384 (0x0501)",
        "rsa_pss_rsae_sha512 (0x0806)",
        "rsa_pkcs1_sha512 (0x0601)"
      ]
    },
    {
      "type": "extended_master_secret",
      "decimal": 23,
      "values": []
    },
    {
      "type": "ec_point_formats",
      "decimal": 11,
      "values": [
        "uncompressed (0)"
      ]
    },
    {
      "type": "server_name",
      "decimal": 0,
      "values": [
        "0000 - 00 1c 00 00 19 74 6c 73-2e 64 61 2d 63 6f 6c   .....tls.da-col",
        "000f - 6c 65 63 74 2e 75 6c 69-78 65 65 2e 6f 72 67   lect.ulixee.org"
      ]
    },
    {
      "type": "UNKNOWN",
      "decimal": 65037,
      "values": [
        "0000 - 00 00 01 00 01 df 00 20-28 d7 6c 70 ef 76 e8   ....... (.lp.v.",
        "000f - 4d 4a f3 92 61 14 03 d2-ff cc be bb 04 8f a5   MJ..a..........",
        "001e - ab f2 ad 64 d1 1c 03 8b-a5 6e 00 b0 ed 7d 96   ...d.....n...}.",
        "002d - 16 9d be 83 98 45 e8 58-3b ab 0f 01 46 24 60   .....E.X;...F$`",
        "003c - 42 85 48 72 cc 6d fc bb-a3 1f d4 c4 8a 29 bb   B.Hr.m.......).",
        "004b - b4 40 1e 43 fd cd 98 7d-06 fc 8e ca 35 c6 5d   .@.C...}....5.]",
        "005a - df 5e 3e ca e5 8b 4a 6d-8a db d5 a7 d3 3d a2   .^>...Jm.....=.",
        "0069 - 7a f7 a6 12 a0 f7 67 de-ea 04 03 cf 39 20 88   z.....g.....9 .",
        "0078 - 6c f9 21 06 83 0c 9f 6f-46 24 f1 1f b1 fa 57   l.!....oF$....W",
        "0087 - 32 9e e4 4c a2 9e 89 ce-09 83 45 db d5 43 17   2..L......E..C.",
        "0096 - 8c a4 56 b7 1c 97 87 d7-32 60 0b 55 1f 5c b6   ..V.....2`.U.\\.",
        "00a5 - e0 ed 61 45 09 41 28 ce-d3 8c 44 82 f8 b8 4f   ..aE.A(...D...O",
        "00b4 - 2e 04 82 21 b5 9a dd 13-7d c5 b4 06 fc 53 96   ...!....}....S.",
        "00c3 - 5b 09 29 61 af be 76 b0-55 43 b7 6a 4b 21 04   [.)a..v.UC.jK!.",
        "00d2 - c2 1c 11 cc 2a 35 8c ef-                       ....*5.."
      ]
    },
    {
      "type": "UNKNOWN",
      "decimal": 17513,
      "values": [
        "0000 - 00 03 02 68 32                                 ...h2"
      ]
    },
    {
      "type": "application_layer_protocol_negotiation",
      "decimal": 16,
      "values": [
        "h2",
        "http/1.1"
      ]
    },
    {
      "type": "compress_certificate",
      "decimal": 27,
      "values": [
        "0000 - 02 00 02                                       ..."
      ]
    },
    {
      "type": "key_share",
      "decimal": 51,
      "values": [
        "NamedGroup: GREASE (64250)",
        "key_exchange:  (len=1): 00",
        "NamedGroup: ecdh_x25519 (29)",
        "key_exchange:  (len=32): A33141DA73037C97DCDD45BA7A15D82DF824D9BFD068BB805464F3EC54E9A002"
      ]
    },
    {
      "type": "GREASE",
      "decimal": 60138,
      "values": [
        "0000 - 00                                             ."
      ]
    }
  ]
}
